trello_cli_example/__init__.py
trello_cli_example/config.py
trello_cli_example/trello_cli.py
Trello_CLI_Example_hanabou-1.0.2.dist-info/LICENSE
Trello_CLI_Example_hanabou-1.0.2.dist-info/METADATA
Trello_CLI_Example_hanabou-1.0.2.dist-info/WHEEL
Trello_CLI_Example_hanabou-1.0.2.dist-info/entry_points.txt
Trello_CLI_Example_hanabou-1.0.2.dist-info/top_level.txt
Trello_CLI_Example_hanabou-1.0.2.dist-info/RECORD
