Metadata-Version: 2.1
Name: Trello-CLI-Example-hanabou
Version: 1.0.2
Summary: Example CLI Script to Create Trello Cards
Home-page: https://github.com/hanaboughannam/Trello-CLI-Example
Author: Hana Bou-Ghannam
Author-email: hanaboughannam@gmail.com
License: MIT
Platform: UNKNOWN
Classifier: Programming Language :: Python :: 3
Classifier: License :: OSI Approved :: MIT License
Classifier: Operating System :: OS Independent
Requires-Python: >=3.6
Requires-Dist: requests (==2.25.1)
Requires-Dist: docopt (==0.6.2)
